iromlab/__init__.py
iromlab/__main__.py
iromlab/cdinfo.py
iromlab/cdworker.py
iromlab/config.py
iromlab/configure.pyw
iromlab/dbpoweramp.py
iromlab/drivers.py
iromlab/iromlab.py
iromlab/iromlab.pyw
iromlab/isobuster.py
iromlab/mdo.py
iromlab/shared.py
iromlab/testsru.py
iromlab/verifyaudio.py
iromlab/conf/config.xml
iromlab/kbapi/__init__.py
iromlab/kbapi/sru.py
iromlab/socketserver/__init__.py
iromlab/socketserver/server.py
iromlab/tools/flac/COPYING.FDL
iromlab/tools/flac/COPYING.GPL
iromlab/tools/flac/COPYING.LGPL
iromlab/tools/flac/COPYING.Xiph
iromlab/tools/flac/html/changelog.html
iromlab/tools/flac/html/developers.html
iromlab/tools/flac/html/documentation.html
iromlab/tools/flac/html/documentation_bugs.html
iromlab/tools/flac/html/documentation_example_code.html
iromlab/tools/flac/html/documentation_format_overview.html
iromlab/tools/flac/html/documentation_tools.html
iromlab/tools/flac/html/documentation_tools_flac.html
iromlab/tools/flac/html/documentation_tools_metaflac.html
iromlab/tools/flac/html/faq.html
iromlab/tools/flac/html/favicon.ico
iromlab/tools/flac/html/features.html
iromlab/tools/flac/html/flac.css
iromlab/tools/flac/html/format.html
iromlab/tools/flac/html/id.html
iromlab/tools/flac/html/index.html
iromlab/tools/flac/html/license.html
iromlab/tools/flac/html/ogg_mapping.html
iromlab/tools/flac/html/images/logo.svg
iromlab/tools/flac/html/images/logo130.gif
iromlab/tools/flac/win32/flac.exe
iromlab/tools/flac/win32/metaflac.exe
iromlab/tools/flac/win64/flac.exe
iromlab/tools/flac/win64/metaflac.exe
iromlab/tools/libcdio/readme.md
iromlab/tools/libcdio/win64/cd-drive.exe
iromlab/tools/libcdio/win64/cd-info.exe
iromlab/tools/libcdio/win64/cd-paranoia.exe
iromlab/tools/libcdio/win64/cd-read.exe
iromlab/tools/libcdio/win64/iso-info.exe
iromlab/tools/libcdio/win64/iso-read.exe
iromlab/tools/libcdio/win64/libcddb-2.dll
iromlab/tools/libcdio/win64/libcdio++-0.dll
iromlab/tools/libcdio/win64/libcdio-16.dll
iromlab-1.0.9.dist-info/LICENSE
iromlab-1.0.9.dist-info/METADATA
iromlab-1.0.9.dist-info/WHEEL
iromlab-1.0.9.dist-info/entry_points.txt
iromlab-1.0.9.dist-info/top_level.txt
iromlab-1.0.9.dist-info/RECORD
