Metadata-Version: 2.1
Name: iromlab
Version: 1.0.9
Summary: Image and Rip Optical Media Like A Boss
Home-page: https://github.com/KBNLresearch/iromlab
Author: Johan van der Knijff
Author-email: johan.vanderknijff@kb.nl
Maintainer: Johan van der Knijff
Maintainer-email: johan.vanderknijff@kb.nl
License: Apache License 2.0
Download-URL: https://github.com/KBNLresearch/iromlab/archive/1.0.9.tar.gz
Platform: Windows
Classifier: Programming Language :: Python :: 3
Requires-Python: >=3.2
Requires-Dist: isolyzer (>=1.3.1)
Requires-Dist: lxml
Requires-Dist: pypiwin32
Requires-Dist: requests
Requires-Dist: setuptools
Requires-Dist: wmi
